deltaconv_bindings.cpython-36m-x86_64-linux-gnu.so
deltaconv-1.0.2.dist-info/WHEEL
deltaconv-1.0.2.dist-info/METADATA
deltaconv-1.0.2.dist-info/RECORD
deltaconv-1.0.2.dist-info/top_level.txt
deltaconv-1.0.2.dist-info/LICENSE
deltaconv.libs/libgomp-a34b3233.so.1.0.0
deltaconv/__init__.py
deltaconv/transforms/__init__.py
deltaconv/transforms/geodesic_fps.py
deltaconv/transforms/random_normals.py
deltaconv/transforms/normalize_axes.py
deltaconv/transforms/random_rotate.py
deltaconv/transforms/normalize_area.py
deltaconv/transforms/sample_points.py
deltaconv/transforms/random_scale.py
deltaconv/transforms/random_translate_global.py
deltaconv/transforms/normalize_scale.py
deltaconv/nn/__init__.py
deltaconv/nn/nonlin.py
deltaconv/nn/mlp.py
deltaconv/nn/deltaconv.py
deltaconv/geometry/__init__.py
deltaconv/geometry/connection.py
deltaconv/geometry/fps.py
deltaconv/geometry/operators.py
deltaconv/geometry/grad_div.py
deltaconv/geometry/grad_div_mls.py
deltaconv/geometry/utils.py
deltaconv/geometry/grad_fem.py
deltaconv/models/__init__.py
deltaconv/models/deltanet_segmentation.py
deltaconv/models/deltanet_classification.py
deltaconv/models/deltanet_base.py
