Metadata-Version: 2.1
Name: deltaconv
Version: 1.0.2
Summary: Implementation of DeltaConv: an anisotropic operator for geometric deep learning on point clouds (and other discretizations that will be added in the future).
Home-page: https://github.com/rubenwiersma/deltaconv
Author: Ruben Wiersma
Author-email: rubenwiersma@gmail.com
License: MIT
Project-URL: Bug Tracker, https://github.com/rubenwiersma/deltaconv/issues
Platform: UNKNOWN
Classifier: Programming Language :: Python :: 3
Classifier: License :: OSI Approved :: Apache Software License
Classifier: Operating System :: OS Independent
Requires-Python: >=3.6
License-File: LICENSE
